{
	"sn": "facebook",
	"custom": {},
	"lastEventDate": "24.04.2023 09:04 Farm1-3_Eu",
	"status": 2,
	"id": "100091335458298",
	"name": "",
	"amountFriends": "",
	"screenname": "Celina Pinheiro",
	"birthdate": "1999 November 1",
	"country": "",
	"isAvatarExists": false,
	"cookie": [
		{
			"domain": ".facebook.com",
			"expirationDate": 1714541359.907863,
			"hostOnly": false,
			"httpOnly": true,
			"name": "dbln",
			"path": "/login/device-based/",
			"sameSite": "no_restriction",
			"secure": true,
			"session": false,
			"storeId": "0",
			"value": "%7B%22100091335458298%22%3A%22ya2Rvccq%22%7D"
		},
		{
			"domain": ".facebook.com",
			"expirationDate": 1714541353.772021,
			"hostOnly": false,
			"httpOnly": true,
			"name": "sb",
			"path": "/",
			"sameSite": "no_restriction",
			"secure": true,
			"session": false,
			"storeId": "0",
			"value": "ZasRZAkKrYOz20Vde4VLDmZM"
		},
		{
			"domain": ".facebook.com",
			"expirationDate": 1714541349.513396,
			"hostOnly": false,
			"httpOnly": true,
			"name": "datr",
			"path": "/",
			"sameSite": "no_restriction",
			"secure": true,
			"session": false,
			"storeId": "0",
			"value": "b5AeZK2i94o4df2qjfD8BcQL"
		},
		{
			"domain": ".facebook.com",
			"expirationDate": 1713861507.795611,
			"hostOnly": false,
			"httpOnly": false,
			"name": "c_user",
			"path": "/",
			"sameSite": "no_restriction",
			"secure": true,
			"session": false,
			"storeId": "0",
			"value": "100091335458298"
		},
		{
			"domain": ".facebook.com",
			"expirationDate": 1713861507.795696,
			"hostOnly": false,
			"httpOnly": true,
			"name": "xs",
			"path": "/",
			"sameSite": "no_restriction",
			"secure": true,
			"session": false,
			"storeId": "0",
			"value": "22%3AtAEJ4JHSTXMBBg%3A2%3A1679981350%3A-1%3A5538%3A%3AAcVkL7uC6sTx_yUGP03-bbX27O72YV5cVNg1qeKIZg"
		},
		{
			"domain": ".facebook.com",
			"expirationDate": 1682931784,
			"hostOnly": false,
			"httpOnly": false,
			"name": "wd",
			"path": "/",
			"sameSite": "lax",
			"secure": true,
			"session": false,
			"storeId": "0",
			"value": "2560x892"
		},
		{
			"domain": ".facebook.com",
			"expirationDate": 1690102908.831892,
			"hostOnly": false,
			"httpOnly": true,
			"name": "fr",
			"path": "/",
			"sameSite": "no_restriction",
			"secure": true,
			"session": false,
			"storeId": "0",
			"value": "0InCMyIeFuCUXhKMf.AWVniYmelD_d7J_m8YjxhPpYm9A.BkRkAE.Up.AAA.0.0.BkRkV9.AWW-bhmjj3c"
		},
		{
			"domain": ".facebook.com",
			"hostOnly": false,
			"httpOnly": false,
			"name": "presence",
			"path": "/",
			"sameSite": "unspecified",
			"secure": true,
			"session": true,
			"storeId": "0",
			"value": "C%7B%22t3%22%3A%5B%5D%2C%22utc3%22%3A1682326969722%2C%22v%22%3A1%7D"
		}
	]
}